{
  "229": [
    [
      {
        "intent": "salutations",
        "uid": "0"
      }
    ],
    [
      {
        "intent": "inform",
        "slot": "symptom",
        "value": "hemoptysis,colored/excess sputum",
        "status": "Yes",
        "uid": "1"
      }
    ],
    [
      {
        "intent": "inquire",
        "slot": "medical history",
        "value": "past experience",
        "uid": "2"
      }
    ],
    [
      {
        "intent": "inform",
        "slot": "medical history",
        "value": "past experience",
        "status": "No",
        "uid": "3"
      }
    ],
    [
      {
        "intent": "inquire",
        "slot": "symptom",
        "value": "cough",
        "uid": "4"
      }
    ],
    [
      {
        "intent": "inform",
        "slot": "symptom",
        "value": "cough",
        "status": "Yes",
        "uid": "5"
      }
    ],
    [
      {
        "intent": "inquire",
        "slot": "symptom",
        "value": "cough",
        "when check": true,
        "uid": "6"
      }
    ],
    [
      {
        "intent": "inform",
        "slot": "symptom",
        "value": "cough",
        "status": "Yes",
        "when": "about four weeks ago ",
        "uid": "7"
      }
    ],
    [
      {
        "intent": "inquire",
        "slot": "exposure",
        "value": "person",
        "uid": "8"
      }
    ],
    [
      {
        "intent": "inform",
        "slot": "travel",
        "status": "Yes",
        "destination": "Haiti ",
        "uid": "9"
      },
      {
        "intent": "inform",
        "slot": "exposure",
        "value": "person",
        "status": "Yes",
        "uid": "9"
      }
    ],
    [
      {
        "intent": "inquire",
        "slot": "exposure",
        "value": "person",
        "status": "Yes",
        "other": "Confirmation for distancing ",
        "uid": "10"
      }
    ],
    [
      {
        "intent": "inform",
        "slot": "exposure",
        "value": "person",
        "status": "Yes",
        "other": "nearby distancing ",
        "uid": "11"
      }
    ],
    [
      {
        "intent": "inquire",
        "slot": "exposure",
        "value": "person",
        "status": "Yes",
        "other": "confirmation for tuberculosis",
        "uid": "12"
      }
    ],
    [
      {
        "intent": "inform",
        "slot": "exposure",
        "value": "person",
        "status": "Yes",
        "other": "yes tuberculosis patients was there",
        "uid": "13"
      }
    ],
    [
      {
        "intent": "inquire",
        "slot": "symptom",
        "value": "cough",
        "characteristics check": true,
        "uid": "14"
      }
    ],
    [
      {
        "intent": "inform",
        "slot": "symptom",
        "value": "colored/excess sputum",
        "status": "Yes",
        "color": "white and yellow",
        "uid": "15"
      }
    ],
    [
      {
        "intent": "inquire",
        "slot": "symptom",
        "value": "colored/excess sputum",
        "other": "confirmation for symptom time until this morning",
        "uid": "16"
      }
    ],
    [
      {
        "intent": "inform",
        "slot": "symptom",
        "value": "colored/excess sputum",
        "status": "Yes",
        "other": "yes until this morning ",
        "uid": "17"
      }
    ],
    [
      {
        "intent": "inquire",
        "slot": "symptom",
        "value": "hemoptysis",
        "other": "confirmation for the amount of blood in the sputum ",
        "uid": "18"
      }
    ],
    [
      {
        "intent": "inform",
        "slot": "symptom",
        "value": "hemoptysis",
        "status": "Yes",
        "other": "it was bright red and it was covering the, the issue",
        "uid": "19"
      }
    ],
    [
      {
        "intent": "inquire",
        "slot": "medical history",
        "value": "past experience",
        "uid": "20"
      }
    ],
    [
      {
        "intent": "inform",
        "slot": "medical history",
        "value": "hemoptysis",
        "status": "No",
        "uid": "21"
      }
    ],
    [
      {
        "intent": "inquire",
        "slot": "symptom",
        "value": "hemoptysis",
        "frequency check": true,
        "other": "did it recur at all",
        "uid": "22"
      }
    ],
    [
      {
        "intent": "inform",
        "slot": "symptom",
        "value": "hemoptysis",
        "status": "Yes",
        "other": " just this morning on the tissue and then a little bit in the toilet",
        "uid": "23"
      }
    ],
    [
      {
        "intent": "inquire",
        "slot": "symptom",
        "value": "cough",
        "duration check": true,
        "uid": "24"
      }
    ],
    [
      {
        "intent": "inform",
        "slot": "symptom",
        "value": "cough",
        "status": "Yes",
        "duration": " through throughout the day",
        "uid": "25"
      }
    ],
    [
      {
        "intent": "inquire",
        "slot": "symptom",
        "value": "cough",
        "ana factors check": true,
        "uid": "26"
      }
    ],
    [
      {
        "intent": "inform",
        "slot": "symptom",
        "value": "cough",
        "status": "Yes",
        "other": "nothing make it worse",
        "uid": "27"
      }
    ],
    [
      {
        "intent": "inquire",
        "slot": "symptom",
        "value": "dyspnea,sore throat,runny nose,runny nose",
        "uid": "28"
      }
    ],
    [
      {
        "intent": "inform",
        "slot": "symptom",
        "value": "dyspnea,runny nose,runny nose",
        "status": "Yes",
        "uid": "29"
      },
      {
        "intent": "inform",
        "slot": "symptom",
        "value": "sore throat",
        "status": "Not sure",
        "uid": "29"
      }
    ],
    [
      {
        "intent": "inquire",
        "slot": "symptom",
        "value": "nausea,vomiting,head ache",
        "uid": "30"
      }
    ],
    [
      {
        "intent": "inform",
        "slot": "symptom",
        "value": "nausea",
        "status": "Yes",
        "uid": "31"
      },
      {
        "intent": "inform",
        "slot": "symptom",
        "value": "vomiting,head ache",
        "status": "No",
        "uid": "31"
      }
    ],
    [
      {
        "intent": "inquire",
        "slot": "symptom",
        "value": "nausea",
        "ana factors check": true,
        "uid": "32"
      }
    ],
    [
      {
        "intent": "inform",
        "slot": "symptom",
        "value": "nausea",
        "status": "Yes",
        "ana factors": "cough",
        "ana factors status": "yes aggravating",
        "uid": "33"
      }
    ],
    [
      {
        "intent": "inquire",
        "slot": "symptom",
        "value": "fever,chills",
        "uid": "34"
      }
    ],
    [
      {
        "intent": "inform",
        "slot": "symptom",
        "value": "fever,sleep hydrosis",
        "status": "Yes",
        "uid": "35"
      },
      {
        "intent": "inform",
        "slot": "symptom",
        "value": "chills",
        "status": "No",
        "uid": "35"
      }
    ],
    [
      {
        "intent": "inquire",
        "slot": "symptom",
        "value": "sleep hydrosis",
        "frequency check": true,
        "uid": "36"
      }
    ],
    [
      {
        "intent": "inform",
        "slot": "symptom",
        "value": "sleep hydrosis",
        "status": "Yes",
        "frequency": "few times in past week",
        "uid": "37"
      }
    ],
    [
      {
        "intent": "inquire",
        "slot": "medical test",
        "name": "temperature ",
        "uid": "38"
      }
    ],
    [
      {
        "intent": "inform",
        "slot": "medical test",
        "name": "temperature ",
        "status": "No",
        "uid": "39"
      }
    ],
    [
      {
        "intent": "inquire",
        "slot": "symptom",
        "value": "fatigue extended",
        "uid": "40"
      }
    ],
    [
      {
        "intent": "inform",
        "slot": "symptom",
        "value": "fatigue extended",
        "status": "Yes",
        "uid": "41"
      }
    ],
    [
      {
        "intent": "inquire",
        "slot": "symptom",
        "value": "dyspnea",
        "uid": "42"
      }
    ],
    [
      {
        "intent": "inform",
        "slot": "symptom",
        "value": "dyspnea",
        "status": "Yes",
        "other": " Just after the coughing  but otherwise no.",
        "uid": "43"
      }
    ],
    [
      {
        "intent": "inquire",
        "slot": "symptom",
        "value": "chest pain",
        "uid": "44"
      }
    ],
    [
      {
        "intent": "inform",
        "slot": "symptom",
        "value": "chest pain",
        "status": "No",
        "uid": "45"
      }
    ],
    [
      {
        "intent": "inquire",
        "slot": "symptom",
        "value": "palpitation",
        "uid": "46"
      }
    ],
    [
      {
        "intent": "inform",
        "slot": "symptom",
        "value": "palpitation",
        "status": "No",
        "uid": "47"
      }
    ],
    [
      {
        "intent": "inquire",
        "slot": "symptom",
        "value": "swelling",
        "location": "limbs",
        "uid": "48"
      }
    ],
    [
      {
        "intent": "inform",
        "slot": "symptom",
        "value": "swelling",
        "status": "No",
        "location": "limbs",
        "uid": "49"
      }
    ],
    [
      {
        "intent": "inquire",
        "slot": "symptom",
        "value": "loss of sense,taste loss,smell loss",
        "uid": "50"
      }
    ],
    [
      {
        "intent": "inform",
        "slot": "symptom",
        "value": "loss of sense,taste loss,smell loss",
        "status": "No",
        "uid": "51"
      }
    ],
    [
      {
        "intent": "inquire",
        "slot": "symptom",
        "value": "bowel movement",
        "uid": "52"
      }
    ],
    [
      {
        "intent": "inform",
        "slot": "symptom",
        "value": "bowel movement",
        "status": "No",
        "uid": "53"
      }
    ],
    [
      {
        "intent": "inquire",
        "slot": "symptom",
        "value": "urination",
        "uid": "54"
      }
    ],
    [
      {
        "intent": "inform",
        "slot": "symptom",
        "value": "urination",
        "status": "No",
        "uid": "55"
      }
    ],
    [
      {
        "intent": "inquire",
        "slot": "symptom",
        "value": "sleep changes",
        "uid": "56"
      }
    ],
    [
      {
        "intent": "inform",
        "slot": "symptom",
        "value": "sleep changes",
        "status": "Yes",
        "other": "haven't been sleeping as well, waking up all sweaty and the cough",
        "uid": "57"
      }
    ],
    [
      {
        "intent": "inquire",
        "slot": "symptom",
        "value": "loss of appetite",
        "uid": "58"
      }
    ],
    [
      {
        "intent": "inform",
        "slot": "symptom",
        "value": "loss of appetite",
        "status": "No",
        "uid": "59"
      }
    ],
    [
      {
        "intent": "inquire",
        "slot": "symptom",
        "value": "unexplained weight loss",
        "uid": "60"
      }
    ],
    [
      {
        "intent": "inform",
        "slot": "symptom",
        "value": "unexplained weight loss",
        "status": "Yes",
        "other": "down like 15 pounds since the summer time",
        "uid": "61"
      }
    ],
    [
      {
        "intent": "inquire",
        "slot": "symptom",
        "value": "unexplained weight loss",
        "uid": "62"
      }
    ],
    [
      {
        "intent": "inform",
        "slot": "medical history",
        "value": "appendix out",
        "status": "The patient still suffers from the condition.",
        "when": "few months ago",
        "uid": "63"
      },
      {
        "intent": "inform",
        "slot": "symptom",
        "value": "unexplained weight loss",
        "status": "Yes",
        "when": "few months ago",
        "uid": "63"
      }
    ],
    [
      {
        "intent": "inquire",
        "slot": "exposure",
        "value": "fumes,dust,animal",
        "uid": "64"
      }
    ],
    [
      {
        "intent": "inform",
        "slot": "exposure",
        "value": "fumes,dust,animal",
        "uid": "65",
        "status": "No"
      }
    ],
    [
      {
        "intent": "inquire",
        "slot": "medical history",
        "other": "confirmation for any medical condition",
        "uid": "66"
      }
    ],
    [
      {
        "intent": "inform",
        "slot": "medical history",
        "other": "no other medical history",
        "uid": "67"
      }
    ],
    [
      {
        "intent": "inquire",
        "slot": "medical history",
        "value": "asthma",
        "uid": "68"
      }
    ],
    [
      {
        "intent": "inform",
        "slot": "medical history",
        "value": "asthma",
        "status": "No",
        "uid": "69"
      }
    ],
    [
      {
        "intent": "inquire",
        "slot": "medication",
        "uid": "70"
      }
    ],
    [
      {
        "intent": "inform",
        "slot": "medication",
        "value": "oral contraceptive pill",
        "status": "currently taking",
        "uid": "71"
      }
    ],
    [
      {
        "intent": "inquire",
        "slot": "medication",
        "value": "oral contraceptive pill",
        "status": "currently taking",
        "since when check": true,
        "uid": "72"
      }
    ],
    [
      {
        "intent": "inform",
        "slot": "medication",
        "value": "oral contraceptive pill",
        "status": "currently taking",
        "since when": "Five years ago",
        "uid": "73"
      }
    ],
    [
      {
        "intent": "inquire",
        "slot": "medical history",
        "value": "allergy medication,allergy,environmental allergies",
        "uid": "74"
      }
    ],
    [
      {
        "intent": "inform",
        "slot": "medical history",
        "value": "allergy,environmental allergies",
        "status": "No",
        "uid": "75"
      },
      {
        "intent": "inform",
        "slot": "medical history",
        "value": "allergy medication",
        "status": "Yes",
        "other": "allergic from septra",
        "uid": "75"
      }
    ],
    [
      {
        "intent": "inquire",
        "slot": "medical history",
        "value": "recent hospitalizaiton",
        "uid": "76"
      }
    ],
    [
      {
        "intent": "inform",
        "slot": "medical history",
        "value": "recent hospitalizaiton",
        "status": "No",
        "uid": "77"
      }
    ],
    [
      {
        "intent": "inquire",
        "slot": "medical history",
        "value": "surgery",
        "other": "confirmation for any other surgery",
        "uid": "78"
      }
    ],
    [
      {
        "intent": "inform",
        "slot": "medical history",
        "value": "surgery",
        "status": "No",
        "other": "no other surgery",
        "uid": "79"
      }
    ],
    [
      {
        "intent": "inquire",
        "slot": "family history",
        "value": "asthma,lung disease,cancer",
        "uid": "80"
      }
    ],
    [
      {
        "intent": "inform",
        "slot": "family history",
        "value": "lung cancer",
        "status": "Yes",
        "relation": "grandfather",
        "uid": "81"
      },
      {
        "intent": "inform",
        "slot": "family history",
        "value": "diabetes",
        "status": "Yes",
        "relation": "Mother",
        "uid": "81"
      },
      {
        "intent": "inform",
        "slot": "family history",
        "value": "lung disease",
        "status": "No",
        "uid": "81"
      }
    ],
    [
      {
        "intent": "inquire",
        "slot": "family history",
        "value": "heart attack,autoimmune condition",
        "uid": "82"
      }
    ],
    [
      {
        "intent": "inform",
        "slot": "family history",
        "value": "autoimmune condition",
        "status": "No",
        "uid": "83"
      }
    ],
    [
      {
        "intent": "inquire",
        "slot": "residence",
        "uid": "84"
      }
    ],
    [
      {
        "intent": "inform",
        "slot": "residence",
        "status": "Yes",
        "other": "living with roommates",
        "uid": "85"
      }
    ],
    [
      {
        "intent": "inquire",
        "slot": "occupation",
        "uid": "86"
      }
    ],
    [
      {
        "intent": "inform",
        "slot": "occupation",
        "value": "Stuedent",
        "status": "Yes",
        "uid": "87"
      }
    ],
    [
      {
        "intent": "inquire",
        "slot": "habit",
        "value": "smoking",
        "uid": "88"
      }
    ],
    [
      {
        "intent": "inform",
        "slot": "habit",
        "value": "smoking",
        "status": "Yes",
        "frquency": "a pack of cigarettes a week",
        "uid": "89"
      }
    ],
    [
      {
        "intent": "inquire",
        "slot": "habit",
        "value": "recreational drugs,marijuana",
        "uid": "90"
      }
    ],
    [
      {
        "intent": "inform",
        "slot": "habit",
        "value": "marijuana",
        "status": "Yes",
        "frquency": "one or two joints on on the weekend",
        "uid": "91"
      }
    ],
    [
      {
        "intent": "inquire",
        "slot": "symptom",
        "value": "all",
        "ana factors": "smoking marijuana,smoking cigarettes ",
        "ana factors check": true,
        "uid": "92"
      }
    ],
    [
      {
        "intent": "inform",
        "slot": "symptom",
        "value": "cough",
        "status": "Yes",
        "ana factors": "moking marijuana,smoking cigarettes",
        "ana factors status": "yes aggravating",
        "uid": "93"
      }
    ],
    [
      {
        "intent": "chit-chat",
        "slot": "medical discussion",
        "uid": "94"
      }
    ],
    [
      {
        "intent": "chit-chat",
        "slot": "medical discussion",
        "uid": "95"
      }
    ],
    [
      {
        "intent": "inquire",
        "slot": "habit",
        "value": "recreational drugs",
        "uid": "96"
      }
    ],
    [
      {
        "intent": "inform",
        "slot": "habit",
        "value": "recreational drugs",
        "status": "Yes",
        "frquency": "few times a year",
        "uid": "97"
      }
    ],
    [
      {
        "intent": "inquire",
        "slot": "habit",
        "value": "alcoholism",
        "uid": "98"
      }
    ],
    [
      {
        "intent": "inform",
        "slot": "habit",
        "value": "alcoholism",
        "status": "Maybe",
        "frquency": " on the weekend",
        "uid": "99"
      }
    ],
    [
      {
        "intent": "chit-chat",
        "slot": "medical discussion",
        "uid": "100"
      }
    ],
    [
      {
        "intent": "chit-chat",
        "slot": "medical discussion",
        "uid": "101"
      }
    ],
    [
      {
        "intent": "diagnosis",
        "slot": "disease",
        "value": "Cancer",
        "status": "Maybe",
        "uid": "102"
      },
      {
        "intent": "inform",
        "slot": "medical test",
        "name": "chest x-ray,sputum culture",
        "other": "Future",
        "uid": "102"
      },
      {
        "intent": "inform",
        "slot": "medication",
        "value": "antibiotic regiment ",
        "other": "Future",
        "uid": "102"
      }
    ],
    [
      {
        "intent": "salutations",
        "uid": "103"
      }
    ],
    [
      {
        "intent": "inform",
        "slot": "medical test",
        "name": "Blood work",
        "other": "Future",
        "uid": "104"
      }
    ],
    [
      {
        "intent": "salutations",
        "uid": "105"
      }
    ],
    [
      {
        "intent": "differential",
        "slot": "diseases/conditions",
        "ddx 1": "tuberculosis",
        "ddx 2": "pneumonia",
        "ddx 3": "viral pneumonia",
        "ddx 4": "allergic bronchopulmonary aspergillosis",
        "uid": "106"
      }
    ]
  ]
}