{
  "319": [
    [
      {
        "intent": "salutations",
        "uid": "0"
      }
    ],
    [
      {
        "intent": "inform",
        "slot": "symptom",
        "value": "dyspnea,cough",
        "status": "Yes",
        "when": "two months ago",
        "uid": "1"
      }
    ],
    [
      {
        "intent": "inquire",
        "slot": "symptom",
        "value": "dyspnea,cough",
        "when": "two months ago",
        "when check": true,
        "uid": "2"
      }
    ],
    [
      {
        "intent": "inform",
        "slot": "symptom",
        "value": "dyspnea",
        "status": "Yes",
        "when": "two months ago",
        "uid": "3"
      },
      {
        "intent": "inform",
        "slot": "symptom",
        "value": "cough",
        "status": "Yes",
        "when": "couple years",
        "progression": "gradually getting worse over time",
        "uid": "3"
      },
      {
        "intent": "inform",
        "slot": "habit",
        "value": "smoking",
        "status": "Yes",
        "uid": "3"
      }
    ],
    [
      {
        "intent": "inquire",
        "slot": "symptom",
        "value": "cough",
        "characteristics check": true,
        "uid": "4"
      }
    ],
    [
      {
        "intent": "inform",
        "slot": "symptom",
        "value": "cough",
        "status": "Yes",
        "characteristics": "persistent",
        "characteristics status": "yes",
        "uid": "5"
      }
    ],
    [
      {
        "intent": "inquire",
        "slot": "symptom",
        "value": "dyspnea",
        "when check": true,
        "uid": "6"
      }
    ],
    [
      {
        "intent": "inform",
        "slot": "symptom",
        "value": "dyspnea",
        "status": "Yes",
        "when": "two months ago",
        "uid": "7"
      }
    ],
    [
      {
        "intent": "inquire",
        "slot": "symptom",
        "value": "dyspnea",
        "progression": "gradually getting worse over time",
        "progression check": true,
        "uid": "8"
      }
    ],
    [
      {
        "intent": "inform",
        "slot": "symptom",
        "value": "dyspnea",
        "status": "Yes",
        "progression": "gradually getting worse over time",
        "uid": "9"
      }
    ],
    [
      {
        "intent": "inquire",
        "slot": "symptom",
        "value": "colored/excess sputum",
        "uid": "10"
      }
    ],
    [
      {
        "intent": "inform",
        "slot": "symptom",
        "value": "colored/excess sputum",
        "status": "Yes",
        "frequency": "sometimes",
        "uid": "11"
      }
    ],
    [
      {
        "intent": "inquire",
        "slot": "symptom",
        "value": "colored/excess sputum",
        "color": "color or clear",
        "color check": true,
        "uid": "12"
      }
    ],
    [
      {
        "intent": "inform",
        "slot": "symptom",
        "value": "colored/excess sputum",
        "status": "Yes",
        "color": "pink",
        "uid": "13"
      }
    ],
    [
      {
        "intent": "inquire",
        "slot": "symptom",
        "value": "colored/excess sputum",
        "color": "pink",
        "color check": true,
        "uid": "14"
      }
    ],
    [
      {
        "intent": "inform",
        "slot": "symptom",
        "value": "colored/excess sputum",
        "status": "Yes",
        "color": "pink",
        "uid": "15"
      }
    ],
    [
      {
        "intent": "inquire",
        "slot": "symptom",
        "value": "hemoptysis",
        "uid": "16"
      }
    ],
    [
      {
        "intent": "inform",
        "slot": "symptom",
        "value": "hemoptysis",
        "status": "Yes",
        "frequency": "sometimes",
        "uid": "17"
      }
    ],
    [
      {
        "intent": "inquire",
        "slot": "symptom",
        "value": "hemoptysis",
        "frequency": "sometimes",
        "frequency check": true,
        "uid": "18"
      }
    ],
    [
      {
        "intent": "inform",
        "slot": "symptom",
        "value": "hemoptysis",
        "status": "Yes",
        "other": "Streaks of blood here and there",
        "uid": "19"
      }
    ],
    [
      {
        "intent": "inquire",
        "slot": "symptom",
        "value": "hemoptysis",
        "characteristics": "frank hemoptysis",
        "characteristics check": true,
        "uid": "20"
      }
    ],
    [
      {
        "intent": "inform",
        "slot": "symptom",
        "value": "hemoptysis",
        "status": "Yes",
        "characteristics": "frank hemoptysis",
        "characteristics status": "no",
        "uid": "21"
      }
    ],
    [
      {
        "intent": "inquire",
        "slot": "symptom",
        "value": "all",
        "when": "over the last two months",
        "frequency check": true,
        "uid": "22"
      }
    ],
    [
      {
        "intent": "inform",
        "slot": "symptom",
        "value": "dyspnea",
        "status": "Yes",
        "frequency": "constant over the last two months",
        "uid": "23"
      },
      {
        "intent": "inform",
        "slot": "symptom",
        "value": "cough,,colored/excess sputum,,hemoptysis",
        "status": "Yes",
        "frequency": "comes and goes",
        "uid": "23"
      }
    ],
    [
      {
        "intent": "inquire",
        "slot": "symptom",
        "value": "dyspnea",
        "ana factors": "physical exertion",
        "ana factors check": true,
        "uid": "24"
      }
    ],
    [
      {
        "intent": "inform",
        "slot": "symptom",
        "value": "dyspnea",
        "status": "Yes",
        "ana factors": "physical exertion,movement",
        "ana factors status": "yes aggravating",
        "uid": "25"
      }
    ],
    [
      {
        "intent": "inquire",
        "slot": "symptom",
        "value": "dyspnea",
        "ana factors": "lying down",
        "ana factors check": true,
        "uid": "26"
      }
    ],
    [
      {
        "intent": "inform",
        "slot": "symptom",
        "value": "dyspnea",
        "status": "Yes",
        "ana factors": "lying down",
        "ana factors status": "no aggravating",
        "uid": "27"
      }
    ],
    [
      {
        "intent": "inquire",
        "slot": "symptom",
        "value": "sleep dyspnea",
        "uid": "28"
      }
    ],
    [
      {
        "intent": "inform",
        "slot": "symptom",
        "value": "sleep dyspnea",
        "status": "No",
        "uid": "29"
      },
      {
        "intent": "inform",
        "slot": "symptom",
        "value": "dyspnea",
        "status": "Yes",
        "progression": "gradually getting worse over time",
        "uid": "29"
      }
    ],
    [
      {
        "intent": "inquire",
        "slot": "medication",
        "response to": "dyspnea,cough,colored/excess sputum,hemoptysis",
        "response to check": true,
        "uid": "30"
      }
    ],
    [
      {
        "intent": "inform",
        "slot": "medication",
        "value": "inhalers",
        "status": "currently taking",
        "impact": "Maybe",
        "uid": "31"
      }
    ],
    [
      {
        "intent": "inquire",
        "slot": "medication",
        "response to check": true,
        "uid": "32"
      }
    ],
    [
      {
        "intent": "inform",
        "slot": "medication",
        "value": "inhalers",
        "status": "currently taking",
        "response to": "COPD",
        "uid": "33"
      }
    ],
    [
      {
        "intent": "inquire",
        "slot": "medical history",
        "value": "COPD",
        "when check": true,
        "uid": "34"
      }
    ],
    [
      {
        "intent": "inform",
        "slot": "medical history",
        "value": "COPD",
        "status": "The patient still suffers from the condition.",
        "when": "15 years ago",
        "uid": "35"
      }
    ],
    [
      {
        "intent": "inquire",
        "slot": "medication",
        "value": "puffers",
        "other": "how many puffers are you taking",
        "uid": "36"
      }
    ],
    [
      {
        "intent": "inform",
        "slot": "medication",
        "value": "puffers",
        "status": "currently taking",
        "other": "patient taking two puffers",
        "uid": "37"
      }
    ],
    [
      {
        "intent": "inquire",
        "slot": "medication",
        "value": "puffers",
        "other": "one that patient take when he absolutely need it?",
        "uid": "38"
      }
    ],
    [
      {
        "intent": "inform",
        "slot": "medication",
        "value": "puffers",
        "status": "currently taking",
        "other": "patient have been trying one ",
        "uid": "39"
      }
    ],
    [
      {
        "intent": "inquire",
        "slot": "medication",
        "value": "puffers",
        "impact check": true,
        "uid": "40"
      }
    ],
    [
      {
        "intent": "inform",
        "slot": "medication",
        "value": "puffers",
        "status": "currently taking",
        "impact": "No",
        "uid": "41"
      }
    ],
    [
      {
        "intent": "inquire",
        "slot": "symptom",
        "value": "fever,Chills,runny nose,cold like symptoms",
        "uid": "42"
      }
    ],
    [
      {
        "intent": "inform",
        "slot": "symptom",
        "value": "fever,Chills,runny nose,cold like symptoms",
        "status": "No",
        "uid": "43"
      }
    ],
    [
      {
        "intent": "inquire",
        "slot": "exposure",
        "value": "person",
        "uid": "44"
      }
    ],
    [
      {
        "intent": "inform",
        "slot": "exposure",
        "value": "person",
        "status": "No",
        "other": "patient have been staying at home",
        "uid": "45"
      }
    ],
    [
      {
        "intent": "inquire",
        "slot": "travel",
        "uid": "46"
      }
    ],
    [
      {
        "intent": "inform",
        "slot": "travel",
        "status": "No",
        "uid": "47"
      }
    ],
    [
      {
        "intent": "inquire",
        "slot": "symptom",
        "value": "dizziness,fainting spells",
        "uid": "48"
      }
    ],
    [
      {
        "intent": "inform",
        "slot": "symptom",
        "value": "dizziness,fainting spells",
        "status": "No",
        "uid": "49"
      }
    ],
    [
      {
        "intent": "inquire",
        "slot": "symptom",
        "value": "swelling",
        "location": "legs,hands",
        "location check": true,
        "uid": "50"
      }
    ],
    [
      {
        "intent": "inform",
        "slot": "symptom",
        "value": "swelling",
        "status": "No",
        "location": "legs,hands",
        "uid": "51"
      }
    ],
    [
      {
        "intent": "inquire",
        "slot": "symptom",
        "value": "head ache",
        "uid": "52"
      }
    ],
    [
      {
        "intent": "inform",
        "slot": "symptom",
        "value": "head ache",
        "status": "Yes",
        "severity": "1",
        "ana factors": "stress",
        "ana factors status": "yes aggravating",
        "frequency": "sometimes",
        "uid": "53"
      }
    ],
    [
      {
        "intent": "inquire",
        "slot": "symptom",
        "value": "nausea,vomiting",
        "uid": "54"
      }
    ],
    [
      {
        "intent": "inform",
        "slot": "symptom",
        "value": "nausea,vomiting",
        "status": "No",
        "uid": "55"
      }
    ],
    [
      {
        "intent": "inquire",
        "slot": "symptom",
        "value": "diarrhea,Constipation",
        "uid": "56"
      }
    ],
    [
      {
        "intent": "inform",
        "slot": "symptom",
        "value": "diarrhea,Constipation",
        "status": "No",
        "uid": "57"
      }
    ],
    [
      {
        "intent": "inquire",
        "slot": "symptom",
        "value": "fever,chills",
        "uid": "58"
      }
    ],
    [
      {
        "intent": "inform",
        "slot": "symptom",
        "value": "fever",
        "status": "Yes",
        "severity": "1",
        "uid": "59"
      }
    ],
    [
      {
        "intent": "inquire",
        "slot": "symptom",
        "value": "fever",
        "when check": true,
        "uid": "60"
      }
    ],
    [
      {
        "intent": "inform",
        "slot": "symptom",
        "value": "fever",
        "status": "Yes",
        "when": "a month ago",
        "other": "patient was checking temperature abouut a month ago and noticed that patient had a fever",
        "uid": "61"
      }
    ],
    [
      {
        "intent": "inquire",
        "slot": "symptom",
        "value": "fever",
        "when": "a month ago",
        "when check": true,
        "uid": "62"
      }
    ],
    [
      {
        "intent": "nod_prompt",
        "uid": "63"
      }
    ],
    [
      {
        "intent": "inquire",
        "slot": "symptom",
        "value": "fever",
        "uid": "64"
      }
    ],
    [
      {
        "intent": "inform",
        "slot": "symptom",
        "value": "fever",
        "status": "Yes",
        "other": "feel a little hot",
        "uid": "65"
      }
    ],
    [
      {
        "intent": "inquire",
        "slot": "symptom",
        "value": "sleep hydrosis",
        "uid": "66"
      }
    ],
    [
      {
        "intent": "inform",
        "slot": "symptom",
        "value": "sleep hydrosis",
        "status": "Yes",
        "frequency": "sometimes",
        "uid": "67"
      }
    ],
    [
      {
        "intent": "inquire",
        "slot": "symptom",
        "value": "unexplained weight loss",
        "uid": "68"
      }
    ],
    [
      {
        "intent": "inform",
        "slot": "symptom",
        "value": "unexplained weight loss",
        "status": "No",
        "uid": "69"
      }
    ],
    [
      {
        "intent": "inquire",
        "slot": "symptom",
        "value": "unexplained weight loss",
        "uid": "70"
      }
    ],
    [
      {
        "intent": "inform",
        "slot": "symptom",
        "value": "unexplained weight loss",
        "status": "No",
        "other": "have been eating quite a lot more now with the pandemic and being home, that might be still in the same",
        "uid": "71"
      }
    ],
    [
      {
        "intent": "inquire",
        "slot": "symptom",
        "value": "fatigue extended",
        "uid": "72"
      }
    ],
    [
      {
        "intent": "inform",
        "slot": "symptom",
        "value": "fatigue extended",
        "status": "Yes",
        "uid": "73"
      }
    ],
    [
      {
        "intent": "inquire",
        "slot": "symptom",
        "value": "dyspnea",
        "ana factors": "movement,rest",
        "ana factors check": true,
        "uid": "74"
      }
    ],
    [
      {
        "intent": "inform",
        "slot": "symptom",
        "value": "dyspnea",
        "status": "Yes",
        "ana factors": "movement",
        "ana factors status": "yes aggravating",
        "other": "short of breath all the time",
        "uid": "75"
      }
    ],
    [
      {
        "intent": "inquire",
        "slot": "medication",
        "value": "oxygen",
        "response to": "COPD",
        "response to check": true,
        "other": "use oxygen at home?",
        "uid": "76"
      }
    ],
    [
      {
        "intent": "inform",
        "slot": "medication",
        "value": "oxygen",
        "status": "no",
        "response to": "COPD",
        "uid": "77"
      }
    ],
    [
      {
        "intent": "inquire",
        "slot": "medical history",
        "value": "hospitalizaiton",
        "other": "for COPD",
        "other check": true,
        "uid": "78"
      }
    ],
    [
      {
        "intent": "inform",
        "slot": "medical history",
        "value": "hospitalizaiton",
        "status": "The patient still suffers from the condition.",
        "when": "couple last year",
        "uid": "79"
      }
    ],
    [
      {
        "intent": "inquire",
        "slot": "medical history",
        "value": "hospitalizaiton",
        "other": "couple of hospitalizations",
        "other check": true,
        "uid": "80"
      }
    ],
    [
      {
        "intent": "inform",
        "slot": "medical history",
        "value": "hospitalizaiton",
        "status": "The patient sufferred from the condition in the past.",
        "other": "four hospitalizations last year",
        "uid": "81"
      }
    ],
    [
      {
        "intent": "inquire",
        "slot": "medical history",
        "value": "additional oxygen requirement",
        "uid": "82"
      }
    ],
    [
      {
        "intent": "inform",
        "slot": "medical history",
        "value": "additional oxygen requirement",
        "status": "Yes",
        "uid": "83"
      }
    ],
    [
      {
        "intent": "chit-chat",
        "slot": "medical discussion",
        "topic": "about COPD",
        "uid": "84"
      }
    ],
    [
      {
        "intent": "chit-chat",
        "slot": "medical discussion",
        "topic": "about COPD",
        "uid": "85"
      }
    ],
    [
      {
        "intent": "inquire",
        "slot": "medication",
        "value": "antibiotics",
        "uid": "86"
      }
    ],
    [
      {
        "intent": "inform",
        "slot": "medication",
        "value": "antibiotics",
        "status": "currently taking",
        "uid": "87"
      }
    ],
    [
      {
        "intent": "inquire",
        "slot": "medical history",
        "value": "pneumonia",
        "uid": "88"
      }
    ],
    [
      {
        "intent": "inform",
        "slot": "medical history",
        "value": "pneumonia",
        "status": "No",
        "uid": "89"
      }
    ],
    [
      {
        "intent": "inquire",
        "slot": "symptom",
        "value": "chest pain",
        "uid": "90"
      }
    ],
    [
      {
        "intent": "inform",
        "slot": "symptom",
        "value": "chest pain",
        "status": "Yes",
        "other": "sometimes when patient breathe in very deep",
        "uid": "91"
      }
    ],
    [
      {
        "intent": "inquire",
        "slot": "symptom",
        "value": "palpitation",
        "location": "heart",
        "location check": true,
        "uid": "92"
      }
    ],
    [
      {
        "intent": "inform",
        "slot": "symptom",
        "value": "palpitation",
        "status": "No",
        "location": "heart",
        "uid": "93"
      }
    ],
    [
      {
        "intent": "inquire",
        "slot": "symptom",
        "value": "sleep issues,loss of appetite",
        "uid": "94"
      }
    ],
    [
      {
        "intent": "inform",
        "slot": "symptom",
        "value": "sleep issues,loss of appetite",
        "status": "No",
        "other": "difficulty breathing sometimes it's been hard to sleep",
        "uid": "95"
      }
    ],
    [
      {
        "intent": "inquire",
        "slot": "exposure",
        "value": "fumes,allergens,animals,pets",
        "uid": "96"
      }
    ],
    [
      {
        "intent": "inform",
        "slot": "exposure",
        "value": "fumes,allergens,animals,pets",
        "status": "No",
        "uid": "97"
      }
    ],
    [
      {
        "intent": "inquire",
        "slot": "medical history",
        "uid": "98"
      }
    ],
    [
      {
        "intent": "inform",
        "slot": "medical history",
        "status": "No",
        "uid": "99"
      }
    ],
    [
      {
        "intent": "inquire",
        "slot": "medical history",
        "value": "allergy medication,environmental allergy",
        "uid": "100"
      }
    ],
    [
      {
        "intent": "inform",
        "slot": "medical history",
        "value": "allergy medication,environmental allergy",
        "status": "No",
        "uid": "101"
      },
      {
        "intent": "inform",
        "slot": "medical history",
        "value": "allergy",
        "status": "The patient still suffers from the condition.",
        "other": "allergic to cats",
        "uid": "101"
      }
    ],
    [
      {
        "intent": "inquire",
        "slot": "exposure",
        "value": "pets",
        "other": "cats",
        "uid": "102"
      }
    ],
    [
      {
        "intent": "inform",
        "slot": "exposure",
        "value": "pets",
        "status": "No",
        "other": "do not have a cat",
        "uid": "103"
      }
    ],
    [
      {
        "intent": "inquire",
        "slot": "exposure",
        "value": "cats",
        "uid": "104"
      }
    ],
    [
      {
        "intent": "inform",
        "slot": "exposure",
        "value": "cats",
        "status": "No",
        "uid": "105"
      }
    ],
    [
      {
        "intent": "inquire",
        "slot": "medication",
        "uid": "106"
      }
    ],
    [
      {
        "intent": "inform",
        "slot": "medication",
        "status": "no",
        "uid": "107"
      }
    ],
    [
      {
        "intent": "inquire",
        "slot": "medication",
        "value": "ventolin inhaler",
        "uid": "108"
      }
    ],
    [
      {
        "intent": "inform",
        "slot": "medication",
        "value": "ventolin inhaler",
        "status": "currently taking",
        "uid": "109"
      }
    ],
    [
      {
        "intent": "inquire",
        "slot": "medication",
        "value": "puffers",
        "other": "query about color of puffer",
        "uid": "110"
      }
    ],
    [
      {
        "intent": "inform",
        "slot": "medication",
        "value": "puffers",
        "status": "currently taking",
        "other": "orange color",
        "uid": "111"
      }
    ],
    [
      {
        "intent": "inquire",
        "slot": "medical history",
        "value": "surgery",
        "uid": "112"
      }
    ],
    [
      {
        "intent": "inform",
        "slot": "medical history",
        "value": "surgery",
        "status": "No",
        "uid": "113"
      },
      {
        "intent": "inform",
        "slot": "medical history",
        "value": "knee replacement",
        "status": "The patient still suffers from the condition.",
        "other": "right side",
        "uid": "113"
      }
    ],
    [
      {
        "intent": "inquire",
        "slot": "medical history",
        "value": "knee replacement",
        "when check": true,
        "uid": "114"
      }
    ],
    [
      {
        "intent": "inform",
        "slot": "medical history",
        "value": "knee replacement",
        "status": "The patient still suffers from the condition.",
        "when": "10 years ago",
        "uid": "115"
      }
    ],
    [
      {
        "intent": "inquire",
        "slot": "family history",
        "value": "lung disease,heart disease,cancer",
        "uid": "116"
      }
    ],
    [
      {
        "intent": "inform",
        "slot": "family history",
        "value": "heart disease,cancer",
        "status": "No",
        "uid": "117"
      },
      {
        "intent": "inform",
        "slot": "family history",
        "value": "COPD ",
        "status": "Yes",
        "relation": "father",
        "uid": "117"
      }
    ],
    [
      {
        "intent": "inquire",
        "slot": "family history",
        "value": "lung cancer",
        "uid": "118"
      }
    ],
    [
      {
        "intent": "inform",
        "slot": "family history",
        "value": "lung cancer",
        "status": "No",
        "uid": "119"
      }
    ],
    [
      {
        "intent": "inquire",
        "slot": "occupation",
        "uid": "120"
      }
    ],
    [
      {
        "intent": "inform",
        "slot": "occupation",
        "value": "retired",
        "status": "Yes",
        "uid": "121"
      }
    ],
    [
      {
        "intent": "inquire",
        "slot": "occupation",
        "uid": "122"
      }
    ],
    [
      {
        "intent": "inform",
        "slot": "occupation",
        "value": "Retired as mechanic at Chrysler's",
        "status": "Yes",
        "uid": "123"
      }
    ],
    [
      {
        "intent": "inquire",
        "slot": "exposure",
        "value": "chemicals,asbestos ",
        "where": "at work",
        "where check": true,
        "uid": "124"
      }
    ],
    [
      {
        "intent": "inform",
        "slot": "exposure",
        "value": "chemicals,asbestos ",
        "status": "No",
        "where": "at work",
        "uid": "125"
      }
    ],
    [
      {
        "intent": "inquire",
        "slot": "habit",
        "value": "smoking",
        "when check": true,
        "uid": "126"
      }
    ],
    [
      {
        "intent": "inform",
        "slot": "habit",
        "value": "smoking",
        "status": "Yes",
        "when": "during teenage",
        "uid": "127"
      }
    ],
    [
      {
        "intent": "inquire",
        "slot": "habit",
        "value": "smoking",
        "frquency check": true,
        "uid": "128"
      }
    ],
    [
      {
        "intent": "inform",
        "slot": "habit",
        "value": "smoking",
        "status": "Yes",
        "frquency": "a pack a day",
        "uid": "129"
      }
    ],
    [
      {
        "intent": "inquire",
        "slot": "habit",
        "value": "smoking",
        "other": "Have patient at all tried to quit before",
        "uid": "130"
      }
    ],
    [
      {
        "intent": "inform",
        "slot": "habit",
        "value": "smoking",
        "status": "Yes",
        "other": "patient can't quit smoking",
        "uid": "131"
      }
    ],
    [
      {
        "intent": "chit-chat",
        "slot": "medical discussion",
        "topic": "suggesting to quit smoking",
        "uid": "132"
      }
    ],
    [
      {
        "intent": "nod_prompt",
        "uid": "133"
      }
    ],
    [
      {
        "intent": "inquire",
        "slot": "habit",
        "value": "recreational drugs,marijuana",
        "uid": "134"
      }
    ],
    [
      {
        "intent": "inform",
        "slot": "habit",
        "value": "recreational drugs,marijuana",
        "status": "No",
        "uid": "135"
      }
    ],
    [
      {
        "intent": "inquire",
        "slot": "habit",
        "value": "alcoholism",
        "uid": "136"
      }
    ],
    [
      {
        "intent": "inform",
        "slot": "habit",
        "value": "alcoholism",
        "status": "No",
        "uid": "137"
      }
    ],
    [
      {
        "intent": "chit-chat",
        "slot": "medical discussion",
        "uid": "138"
      }
    ],
    [
      {
        "intent": "chit-chat",
        "slot": "medical discussion",
        "uid": "139"
      }
    ],
    [
      {
        "intent": "inform",
        "slot": "other",
        "other information": "doctor advised patient for ventilation",
        "uid": "140"
      },
      {
        "intent": "inform",
        "slot": "medication",
        "value": "steroid ",
        "other": "will be prescribed",
        "uid": "140"
      },
      {
        "intent": "inform",
        "slot": "medical test",
        "name": "covid swab",
        "other": "future",
        "uid": "140"
      },
      {
        "intent": "inform",
        "slot": "medical test",
        "name": "chest x ray",
        "other": "future",
        "uid": "140"
      },
      {
        "intent": "diagnosis",
        "slot": "disease",
        "value": "pneumonia",
        "status": "Maybe",
        "uid": "140"
      },
      {
        "intent": "inform",
        "slot": "medical test",
        "name": "blood work",
        "other": "future",
        "uid": "140"
      }
    ],
    [
      {
        "intent": "nod_prompt",
        "uid": "141"
      }
    ],
    [
      {
        "intent": "inform",
        "slot": "medication",
        "value": "home oxygen",
        "response to": "COPD",
        "other": "future",
        "uid": "142"
      }
    ],
    [
      {
        "intent": "chit-chat",
        "slot": "medical discussion",
        "uid": "143"
      }
    ],
    [
      {
        "intent": "inform",
        "slot": "medical test",
        "name": "physical examination",
        "other": "future",
        "uid": "144"
      }
    ],
    [
      {
        "intent": "nod_prompt",
        "uid": "145"
      }
    ],
    [
      {
        "intent": "differential",
        "slot": "diseases/conditions",
        "ddx 1": "acute copd exacerbation / infection",
        "ddx 2": "pneumonia",
        "ddx 3": "covid",
        "ddx 4": "influenza",
        "ddx 5": "lung cancer",
        "uid": "146"
      }
    ]
  ]
}