{
  "medical_history_assessed": {
    "aches": {
      "assessed": "Yes",
      "example_quotes": [
        "Some muscle aches, I would say mostly in my arms and just my legs, yeah."
      ]
    },
    "changes_in_appetite": {
      "assessed": "No",
      "example_quotes": []
    },
    "grunting": {
      "assessed": "No",
      "example_quotes": []
    },
    "hyperacusis": {
      "assessed": "No",
      "example_quotes": []
    },
    "injury": {
      "assessed": "No",
      "example_quotes": []
    },
    "lightheadedness": {
      "assessed": "No",
      "example_quotes": []
    },
    "odynophagia": {
      "assessed": "No",
      "example_quotes": []
    },
    "phlegm": {
      "assessed": "No",
      "example_quotes": []
    },
    "respiratory_distress_syndrome": {
      "assessed": "No",
      "example_quotes": []
    },
    "sinus_congestion": {
      "assessed": "No",
      "example_quotes": []
    },
    "sneezing": {
      "assessed": "No",
      "example_quotes": []
    },
    "stiffness": {
      "assessed": "No",
      "example_quotes": []
    },
    "tachypnea": {
      "assessed": "No",
      "example_quotes": []
    },
    "throat_pain": {
      "assessed": "No",
      "example_quotes": []
    },
    "trauma": {
      "assessed": "No",
      "example_quotes": []
    },
    "brain_fog": {
      "assessed": "Yes",
      "example_quotes": [
        "I just don't remember, I remember things, but it's it's like I'm doing everything underwater."
      ]
    },
    "chest_pain": {
      "assessed": "Yes",
      "example_quotes": [
        "No."
      ]
    },
    "confusion": {
      "assessed": "No",
      "example_quotes": []
    },
    "constipation": {
      "assessed": "Yes",
      "example_quotes": [
        "No."
      ]
    },
    "cough": {
      "assessed": "Yes",
      "example_quotes": [
        "No cough, no."
      ]
    },
    "diabetes": {
      "assessed": "Yes",
      "example_quotes": [
        "No."
      ]
    },
    "diarrhoea": {
      "assessed": "Yes",
      "example_quotes": [
        "Um no, no diarrhea."
      ]
    },
    "discharge": {
      "assessed": "Yes",
      "example_quotes": [
        "No."
      ]
    },
    "dyspnea": {
      "assessed": "Yes",
      "example_quotes": [
        "No shortness of breath either."
      ]
    },
    "fatigue_extended": {
      "assessed": "Yes",
      "example_quotes": [
        "Yes, I would say I am significantly more tired than I used to be."
      ]
    },
    "fever": {
      "assessed": "Yes",
      "example_quotes": [
        "I didn't actually, no I didn't check my temperature, I just feel hot."
      ]
    },
    "head_ache": {
      "assessed": "Yes",
      "example_quotes": [
        "And just my brain feels foggy. So I thought I should come get it checked out."
      ]
    },
    "high_blood_pressure": {
      "assessed": "Yes",
      "example_quotes": [
        "No."
      ]
    },
    "itchiness": {
      "assessed": "No",
      "example_quotes": []
    },
    "loss_of_smell": {
      "assessed": "Yes",
      "example_quotes": [
        "Um, no."
      ]
    },
    "loss_of_taste": {
      "assessed": "Yes",
      "example_quotes": [
        "Um, no."
      ]
    },
    "memory_loss": {
      "assessed": "No",
      "example_quotes": []
    },
    "nausea": {
      "assessed": "Yes",
      "example_quotes": [
        "No."
      ]
    },
    "pain": {
      "assessed": "Yes",
      "example_quotes": [
        "It you know it feels crampy."
      ]
    },
    "palpitation": {
      "assessed": "Yes",
      "example_quotes": [
        "No."
      ]
    },
    "photophobia": {
      "assessed": "No",
      "example_quotes": []
    },
    "sleep_problem": {
      "assessed": "No",
      "example_quotes": []
    },
    "tearing": {
      "assessed": "No",
      "example_quotes": []
    },
    "tearing_or_or_itchiness": {
      "assessed": "No",
      "example_quotes": []
    },
    "urination": {
      "assessed": "Yes",
      "example_quotes": [
        "No, no changes."
      ]
    },
    "vaginal_discharge": {
      "assessed": "Yes",
      "example_quotes": [
        "No."
      ]
    },
    "vaginal_discomfort": {
      "assessed": "Yes",
      "example_quotes": [
        "No."
      ]
    },
    "vomiting": {
      "assessed": "Yes",
      "example_quotes": [
        "No."
      ]
    },
    "wheez": {
      "assessed": "Yes",
      "example_quotes": [
        "Um no no wheezing."
      ]
    }
  }
}