{
  "medical_history_assessed": {
    "loss_of_consciousness_due_to_alcohol": {
      "assessed": "No",
      "example_quotes": []
    },
    "muscle_ache": {
      "assessed": "No",
      "example_quotes": []
    },
    "allergic_rhinitis": {
      "assessed": "No",
      "example_quotes": []
    },
    "bowel_movement": {
      "assessed": "Yes",
      "example_quotes": [
        "Any changes in her bowel movement, constipation, diarrhea?",
        "No, that's been normal."
      ]
    },
    "change_in_sleep": {
      "assessed": "Yes",
      "example_quotes": [
        "Any issues with their sleep or appetite?",
        "She has been a bit a bit fussy, but she's been sleeping OK."
      ]
    },
    "chest_pain": {
      "assessed": "Yes",
      "example_quotes": [
        "Any chest pain that she's described?",
        "No chest pain."
      ]
    },
    "chills": {
      "assessed": "Yes",
      "example_quotes": [
        "Any other symptoms like fevers, chills, shortness of breath, um, anything like that?",
        "Uh, she did feel a bit warm to touch and has looked a bit flushed in her face. Just doesn't look like herself."
      ]
    },
    "colored_excess_sputum": {
      "assessed": "Yes",
      "example_quotes": [
        "is she at all, coughing up any green or yellow material or any blood at all?",
        "No, nothing like that."
      ]
    },
    "complications_actual_delivery": {
      "assessed": "Yes",
      "example_quotes": [
        "OK and were there any complications at all during your pregnancy with her or after the pregnancy?",
        "No, it was a vaginal delivery at 38 weeks and she was a normal weight. We were able to go home right away with with no complications. So yeah, things were good."
      ]
    },
    "constipation": {
      "assessed": "Yes",
      "example_quotes": [
        "Any changes in her bowel movement, constipation, diarrhea?",
        "No, that's been normal."
      ]
    },
    "cough": {
      "assessed": "Yes",
      "example_quotes": [
        "does she have any coughing at all?",
        "Yeah, so she she did start to cough actually after that so that the cough has been there for the last, for the last maybe two to three days. It's a dry cough."
      ]
    },
    "decreased_concentration": {
      "assessed": "No",
      "example_quotes": []
    },
    "decreased_oral_intake": {
      "assessed": "No",
      "example_quotes": []
    },
    "decreased_physical_activity": {
      "assessed": "No",
      "example_quotes": []
    },
    "delayed_growth_milestones": {
      "assessed": "Yes",
      "example_quotes": [
        "OK, uhm any issues developmentally as she was growing up like to meet are all our milestones at an appropriate age?",
        "She did yeah, she has met she was walking at the appropriate times and able to talk and does work really well in school and is social with with her classmates and peers."
      ]
    },
    "diarrhoea": {
      "assessed": "Yes",
      "example_quotes": [
        "Any changes in her bowel movement, constipation, diarrhea?",
        "No, that's been normal."
      ]
    },
    "drowsiness": {
      "assessed": "No",
      "example_quotes": []
    },
    "dyspnea": {
      "assessed": "Yes",
      "example_quotes": [
        "Any other symptoms like fevers, chills, shortness of breath, um, anything like that?",
        "Uh, she did feel a bit warm to touch and has looked a bit flushed in her face. Just doesn't look like herself."
      ]
    },
    "fatigue_extended": {
      "assessed": "Yes",
      "example_quotes": [
        "Does she behave like herself Like is she more tired at all? More irritable, anything like that?",
        "Yeah, she's been a, maybe a bit more, maybe a bit more tired and and a bit more irritable, but not not too bad. She, she missed school today but went yesterday."
      ]
    },
    "fatigue_sleep": {
      "assessed": "No",
      "example_quotes": []
    },
    "fever": {
      "assessed": "Yes",
      "example_quotes": [
        "Any other symptoms like fevers, chills, shortness of breath, um, anything like that?",
        "Uh, she did feel a bit warm to touch and has looked a bit flushed in her face. Just doesn't look like herself."
      ]
    },
    "food_allergy": {
      "assessed": "No",
      "example_quotes": []
    },
    "head_ache": {
      "assessed": "Yes",
      "example_quotes": [
        "Any headaches, nausea or vomiting?",
        "Uhm, no."
      ]
    },
    "hemoptysis": {
      "assessed": "Yes",
      "example_quotes": [
        "is she at all, coughing up any green or yellow material or any blood at all?",
        "No, nothing like that."
      ]
    },
    "lethargic": {
      "assessed": "Yes",
      "example_quotes": [
        "Does she behave like herself Like is she more tired at all? More irritable, anything like that?",
        "Yeah, she's been a, maybe a bit more, maybe a bit more tired and and a bit more irritable, but not not too bad. She, she missed school today but went yesterday."
      ]
    },
    "loss_of_appetite": {
      "assessed": "No",
      "example_quotes": []
    },
    "low_mood": {
      "assessed": "No",
      "example_quotes": []
    },
    "lung_complications": {
      "assessed": "No",
      "example_quotes": []
    },
    "nasal_congestion": {
      "assessed": "Yes",
      "example_quotes": [
        "OK, and what symptoms started first?",
        "I think the runny nose is what, what started first. And like kind of the nasal congestion. She was telling you that she felt that there was like pressure or congestion in her nose."
      ]
    },
    "nausea": {
      "assessed": "Yes",
      "example_quotes": [
        "Any headaches, nausea or vomiting?",
        "Uhm, no."
      ]
    },
    "numbness": {
      "assessed": "No",
      "example_quotes": []
    },
    "paralysis_limb_or_face": {
      "assessed": "No",
      "example_quotes": []
    },
    "pressure_in_around_face": {
      "assessed": "Yes",
      "example_quotes": [
        "OK, and what symptoms started first?",
        "I think the runny nose is what, what started first. And like kind of the nasal congestion. She was telling you that she felt that there was like pressure or congestion in her nose."
      ]
    },
    "runny_nose": {
      "assessed": "Yes",
      "example_quotes": [
        "Yeah, I'm just bringing in my old daughter who's really been complaining about having a runny nose and has been sneezing a lot over this past over this past week."
      ]
    },
    "sleep_hydrosis": {
      "assessed": "No",
      "example_quotes": []
    },
    "sleep_problem": {
      "assessed": "No",
      "example_quotes": []
    },
    "slow_motion_feeling": {
      "assessed": "No",
      "example_quotes": []
    },
    "smell_loss": {
      "assessed": "Yes",
      "example_quotes": [
        "does, has she lost a sense of taste or smell at all?",
        "No, she hasn't said any anything like that, just the nasal congestion."
      ]
    },
    "sneezing": {
      "assessed": "Yes",
      "example_quotes": [
        "Yeah, I'm just bringing in my old daughter who's really been complaining about having a runny nose and has been sneezing a lot over this past over this past week."
      ]
    },
    "soreness": {
      "assessed": "No",
      "example_quotes": []
    },
    "straining_and_chest_discomfort": {
      "assessed": "No",
      "example_quotes": []
    },
    "sweaty": {
      "assessed": "No",
      "example_quotes": []
    },
    "taste_loss": {
      "assessed": "Yes",
      "example_quotes": [
        "does, has she lost a sense of taste or smell at all?",
        "No, she hasn't said any anything like that, just the nasal congestion."
      ]
    },
    "taste_problem": {
      "assessed": "No",
      "example_quotes": []
    },
    "tonsilitis": {
      "assessed": "No",
      "example_quotes": []
    },
    "unexplained_weight_loss": {
      "assessed": "Yes",
      "example_quotes": [
        "has she lost any weight recently?",
        "No, no no. She's been gaining weight well."
      ]
    },
    "urination": {
      "assessed": "Yes",
      "example_quotes": [
        "Any urinary problems?",
        "No, she had a urinary tract infection when she was like little but hasn't had any since."
      ]
    },
    "vaccine_related_reaction": {
      "assessed": "No",
      "example_quotes": []
    },
    "vaginal_discharge": {
      "assessed": "No",
      "example_quotes": []
    },
    "vomiting": {
      "assessed": "Yes",
      "example_quotes": [
        "Any headaches, nausea or vomiting?",
        "Uhm, no."
      ]
    }
  }
}