{
  "medical_history_assessed": {
    "chest_tightness": {
      "assessed": "No",
      "example_quotes": []
    },
    "colored_excess_sputum": {
      "assessed": "No",
      "example_quotes": []
    },
    "coughing_fit": {
      "assessed": "No",
      "example_quotes": []
    },
    "general_weakness": {
      "assessed": "Yes",
      "example_quotes": [
        "I have felt just tired and, over these last couple of days."
      ]
    },
    "grunting_noise": {
      "assessed": "No",
      "example_quotes": []
    },
    "hyperacusis": {
      "assessed": "No",
      "example_quotes": []
    },
    "infection": {
      "assessed": "Yes",
      "example_quotes": [
        "Given that your symptoms sort of sound like you may have a viral or bacterial infection."
      ]
    },
    "injury": {
      "assessed": "Yes",
      "example_quotes": [
        "I had surgery on my knee when I was a teenager. I uh tore my ACL but it's been good since then."
      ]
    },
    "itching": {
      "assessed": "No",
      "example_quotes": []
    },
    "nausea": {
      "assessed": "No",
      "example_quotes": []
    },
    "paralysis_general": {
      "assessed": "No",
      "example_quotes": []
    },
    "self_harm_thoughts": {
      "assessed": "No",
      "example_quotes": []
    },
    "sensitive_to_allergies": {
      "assessed": "No",
      "example_quotes": []
    },
    "sexually_transmitted_infection": {
      "assessed": "No",
      "example_quotes": []
    },
    "sleep_changes": {
      "assessed": "Yes",
      "example_quotes": [
        "the Tylenol helped me sleep a little bit with that the headache."
      ]
    },
    "soreness": {
      "assessed": "Yes",
      "example_quotes": [
        "I've had a sore throat as well."
      ]
    },
    "tearing": {
      "assessed": "No",
      "example_quotes": []
    },
    "tightness": {
      "assessed": "No",
      "example_quotes": []
    },
    "tingling": {
      "assessed": "No",
      "example_quotes": []
    },
    "vaginal_discomfort": {
      "assessed": "No",
      "example_quotes": []
    },
    "vision_problem": {
      "assessed": "No",
      "example_quotes": []
    },
    "watery_eyes": {
      "assessed": "No",
      "example_quotes": []
    },
    "bowel_movement": {
      "assessed": "Yes",
      "example_quotes": [
        "no changes in your bowel movement, any diarrhea?"
      ]
    },
    "chest_pain": {
      "assessed": "No",
      "example_quotes": []
    },
    "confusion": {
      "assessed": "No",
      "example_quotes": []
    },
    "cough": {
      "assessed": "Yes",
      "example_quotes": [
        "two days ago I started to have this cough."
      ]
    },
    "diarrhoea": {
      "assessed": "No",
      "example_quotes": []
    },
    "dizzyness": {
      "assessed": "No",
      "example_quotes": []
    },
    "dysphagia": {
      "assessed": "Yes",
      "example_quotes": [
        "is a little bit painful, but I've been able to eat and drink okay."
      ]
    },
    "dyspnea": {
      "assessed": "No",
      "example_quotes": []
    },
    "fainting": {
      "assessed": "No",
      "example_quotes": []
    },
    "fatigue_extended": {
      "assessed": "No",
      "example_quotes": []
    },
    "fever": {
      "assessed": "Yes",
      "example_quotes": [
        "I checked it and it was, like just over 38 I think like 38.1 or two."
      ]
    },
    "flu_like_symptoms": {
      "assessed": "Yes",
      "example_quotes": [
        "Have you had any other symptoms? Have you had a confusion or is it any fuzziness? Or any flu like symptoms?"
      ]
    },
    "fuzziness": {
      "assessed": "No",
      "example_quotes": []
    },
    "head_ache": {
      "assessed": "Yes",
      "example_quotes": [
        "I kind of feel it all over."
      ]
    },
    "headache": {
      "assessed": "Yes",
      "example_quotes": [
        "I would say maybe a 5."
      ]
    },
    "nasal_congestion": {
      "assessed": "No",
      "example_quotes": []
    },
    "pain": {
      "assessed": "No",
      "example_quotes": []
    },
    "runny_nose": {
      "assessed": "No",
      "example_quotes": []
    },
    "smell_loss": {
      "assessed": "Yes",
      "example_quotes": [
        "Yeah, I said some actually now that you mention it right sense of smell has been different."
      ]
    },
    "sore_throat": {
      "assessed": "Yes",
      "example_quotes": [
        "I've had a sore throat as well."
      ]
    },
    "taste_loss": {
      "assessed": "No",
      "example_quotes": []
    },
    "urination": {
      "assessed": "Yes",
      "example_quotes": [
        "I haven't had any of those symptoms."
      ]
    }
  }
}