{
  "medical_history_assessed": {
    "anxious": {
      "assessed": "No",
      "example_quotes": []
    },
    "apnea_at_birth": {
      "assessed": "No",
      "example_quotes": []
    },
    "bad_smell": {
      "assessed": "No",
      "example_quotes": []
    },
    "decrease_interest_in_activities": {
      "assessed": "No",
      "example_quotes": []
    },
    "difficulty_talking": {
      "assessed": "Yes",
      "example_quotes": [
        "OK, uhm any issues developmentally as she was growing up like to meet are all our milestones at an appropriate age?",
        "She did yeah, she has met she was walking at the appropriate times and able to talk and does work really well in school and is social with with her classmates and peers."
      ]
    },
    "eye_discharge": {
      "assessed": "No",
      "example_quotes": []
    },
    "eye_redness": {
      "assessed": "No",
      "example_quotes": []
    },
    "general_weakness": {
      "assessed": "Yes",
      "example_quotes": [
        "Just not feeling very well.",
        "Does she behave like herself Like is she more tired at all? More irritable, anything like that?",
        "Yeah, she's been a, maybe a bit more, maybe a bit more tired and and a bit more irritable, but not not too bad."
      ]
    },
    "guilt_feeling": {
      "assessed": "No",
      "example_quotes": []
    },
    "hyperacusis": {
      "assessed": "No",
      "example_quotes": []
    },
    "loss_of_consciousness": {
      "assessed": "No",
      "example_quotes": []
    },
    "low_mood": {
      "assessed": "No",
      "example_quotes": []
    },
    "lumps": {
      "assessed": "No",
      "example_quotes": []
    },
    "not_crying": {
      "assessed": "No",
      "example_quotes": []
    },
    "numbness": {
      "assessed": "No",
      "example_quotes": []
    },
    "palpitation": {
      "assessed": "No",
      "example_quotes": []
    },
    "paralysis_general": {
      "assessed": "No",
      "example_quotes": []
    },
    "photophobia": {
      "assessed": "No",
      "example_quotes": []
    },
    "rectal_bleeding": {
      "assessed": "No",
      "example_quotes": []
    },
    "self_harm_thoughts": {
      "assessed": "No",
      "example_quotes": []
    },
    "slow_motion_feeling": {
      "assessed": "No",
      "example_quotes": []
    },
    "slurred_speech": {
      "assessed": "No",
      "example_quotes": []
    },
    "stiffness": {
      "assessed": "No",
      "example_quotes": []
    },
    "vaginal_discomfort": {
      "assessed": "No",
      "example_quotes": []
    },
    "weight_changes": {
      "assessed": "Yes",
      "example_quotes": [
        "Uhm, has she lost any weight recently?",
        "No, no no. She's been gaining weight well."
      ]
    },
    "bowel_movement": {
      "assessed": "Yes",
      "example_quotes": [
        "OK. Any changes in her bowel movement, constipation, diarrhea?",
        "No, that's been normal."
      ]
    },
    "chest_pain": {
      "assessed": "Yes",
      "example_quotes": [
        "OK, any chest pain that she's described?",
        "No chest pain."
      ]
    },
    "chills": {
      "assessed": "Yes",
      "example_quotes": [
        "OK. Any other symptoms like fevers, chills, shortness of breath, um, anything like that?"
      ]
    },
    "colored_excess_sputum": {
      "assessed": "Yes",
      "example_quotes": [
        "OK, is she at all, coughing up any green or yellow material or any blood at all?",
        "No, nothing like that."
      ]
    },
    "constipation": {
      "assessed": "Yes",
      "example_quotes": [
        "OK. Any changes in her bowel movement, constipation, diarrhea?",
        "No, that's been normal."
      ]
    },
    "cough": {
      "assessed": "Yes",
      "example_quotes": [
        "OK, does she have any coughing at all?",
        "Yeah, so she she did start to cough actually after that so that the cough has been there for the last, for the last maybe two to three days. It's a dry cough."
      ]
    },
    "delayed_growth_milestones": {
      "assessed": "Yes",
      "example_quotes": [
        "OK, uhm any issues developmentally as she was growing up like to meet are all our milestones at an appropriate age?",
        "She did yeah, she has met she was walking at the appropriate times and able to talk and does work really well in school and is social with with her classmates and peers."
      ]
    },
    "diarrhoea": {
      "assessed": "Yes",
      "example_quotes": [
        "OK. Any changes in her bowel movement, constipation, diarrhea?",
        "No, that's been normal."
      ]
    },
    "dyspnea": {
      "assessed": "Yes",
      "example_quotes": [
        "OK. Any other symptoms like fevers, chills, shortness of breath, um, anything like that?"
      ]
    },
    "fatigue_extended": {
      "assessed": "Yes",
      "example_quotes": [
        "Does she behave like herself Like is she more tired at all? More irritable, anything like that?",
        "Yeah, she's been a, maybe a bit more, maybe a bit more tired and and a bit more irritable, but not not too bad. She, she missed school today but went yesterday."
      ]
    },
    "fatigue_sleep": {
      "assessed": "Yes",
      "example_quotes": [
        "OK, any issues with their sleep or appetite?",
        "She has been a bit a bit fussy, but she's been sleeping OK."
      ]
    },
    "fever": {
      "assessed": "Yes",
      "example_quotes": [
        "OK. Any other symptoms like fevers, chills, shortness of breath, um, anything like that?",
        "Uh, she did feel a bit warm to touch and has looked a bit flushed in her face. Just doesn't look like herself."
      ]
    },
    "head_ache": {
      "assessed": "Yes",
      "example_quotes": [
        "Any headaches, nausea or vomiting?",
        "Uhm, no."
      ]
    },
    "hemoptysis": {
      "assessed": "Yes",
      "example_quotes": [
        "OK, is she at all, coughing up any green or yellow material or any blood at all?",
        "No, nothing like that."
      ]
    },
    "loss_of_appetite": {
      "assessed": "Yes",
      "example_quotes": [
        "OK, any issues with their sleep or appetite?",
        "She has been a bit a bit fussy, but she's been sleeping OK."
      ]
    },
    "nasal_congestion": {
      "assessed": "Yes",
      "example_quotes": [
        "I think the runny nose is what, what started first. And like kind of the nasal congestion. She was telling you that she felt that there was like pressure or congestion in her nose."
      ]
    },
    "nausea": {
      "assessed": "Yes",
      "example_quotes": [
        "Any headaches, nausea or vomiting?",
        "Uhm, no."
      ]
    },
    "pressure_in_around_face": {
      "assessed": "Yes",
      "example_quotes": [
        "OK. Did you feel any pressure in around her face at all?",
        "Uh, yeah, well yeah, I think so. She doesn't say, well, no pain but does feel like a bit of pressure with the congestion, I think."
      ]
    },
    "runny_nose": {
      "assessed": "Yes",
      "example_quotes": [
        "Yeah, I'm just bringing in my old daughter who's really been complaining about having a runny nose and has been sneezing a lot over this past over this past week.",
        "I think the runny nose is what, what started first."
      ]
    },
    "smell_loss": {
      "assessed": "Yes",
      "example_quotes": [
        "OK, does, has she lost a sense of taste or smell at all?",
        "No, she hasn't said any anything like that, just the nasal congestion."
      ]
    },
    "sneezing": {
      "assessed": "Yes",
      "example_quotes": [
        "Yeah, I'm just bringing in my old daughter who's really been complaining about having a runny nose and has been sneezing a lot over this past over this past week.",
        "OK, and then this, when did this sneezing start?"
      ]
    },
    "taste_loss": {
      "assessed": "Yes",
      "example_quotes": [
        "OK, does, has she lost a sense of taste or smell at all?",
        "No, she hasn't said any anything like that, just the nasal congestion."
      ]
    },
    "unexplained_weight_loss": {
      "assessed": "Yes",
      "example_quotes": [
        "Uhm, has she lost any weight recently?",
        "No, no no. She's been gaining weight well."
      ]
    },
    "urination": {
      "assessed": "Yes",
      "example_quotes": [
        "OK. Any urinary problems?",
        "No, she had a urinary tract infection when she was like little but hasn't had any since."
      ]
    },
    "vomiting": {
      "assessed": "Yes",
      "example_quotes": [
        "Any headaches, nausea or vomiting?",
        "Uhm, no."
      ]
    }
  }
}