{
  "precision": 0.8787878787878788,
  "recall": 1.0,
  "f1_score": 0.9354838709677419,
  "true_positives": 29,
  "false_positives": 4,
  "false_negatives": 0,
  "total_items": 58,
  "false_positive_details": [
    {
      "item": "Weight Gain",
      "result_quotes": [
        "has your weight been stable over the last several months",
        "Yeah, weight has been stable."
      ]
    },
    {
      "item": "Redness",
      "result_quotes": [
        "How about any viral symptoms, like eye redness, nasal discharge, or nasal congestion or cough?",
        "I have been having a little bit of a cough, but that's it"
      ]
    },
    {
      "item": "High Blood Pressure",
      "result_quotes": [
        "in the past have you been diagnosed with any medical conditions?",
        "No, I've been pretty healthy."
      ]
    },
    {
      "item": "Diabetes",
      "result_quotes": [
        "in the past have you been diagnosed with any medical conditions?",
        "No, I've been pretty healthy."
      ]
    }
  ],
  "false_negative_details": []
}